bush/__init__.py
bush/nn.py
bush/tflite.py
bush/tvm.py
bush/util.py
bush-0.0.1.dist-info/DESCRIPTION.rst
bush-0.0.1.dist-info/METADATA
bush-0.0.1.dist-info/RECORD
bush-0.0.1.dist-info/WHEEL
bush-0.0.1.dist-info/metadata.json
bush-0.0.1.dist-info/top_level.txt
