Metadata-Version: 2.0
Name: bush
Version: 0.0.1
Summary: Toys to play around with machine learning
Home-page: https://jackwish.net/bush
Author: 王振华（Zhenhua WANG）
Author-email: i@jackwish.net
License: UNKNOWN
Project-URL: Bug Reports, https://github.com/jackwish/bush/issues
Project-URL: Source, https://github.com/jackwish/bush
Keywords: machine learning
Platform: UNKNOWN
Classifier: Development Status :: 1 - Planning
Classifier: Programming Language :: Python :: 3
Classifier: Programming Language :: Python :: 3.5
Classifier: Programming Language :: Python :: 3.6
Classifier: Programming Language :: Python :: 3.7
Classifier: Environment :: Console
Classifier: Intended Audience :: Developers
Classifier: License :: OSI Approved :: Apache Software License
Classifier: Natural Language :: English
Classifier: Operating System :: OS Independent
Classifier: Topic :: Scientific/Engineering :: Artificial Intelligence
Requires-Python: !=3.0.*, !=3.1.*, !=3.2.*, !=3.3.*, !=3.4.*, <4
Requires-Dist: flatbuffers
